pgscatalog/calc/__init__.py
pgscatalog/calc/cli/__init__.py
pgscatalog/calc/cli/aggregate_cli.py
pgscatalog/calc/cli/ancestry_cli.py
pgscatalog/calc/lib/__init__.py
pgscatalog/calc/lib/_config.py
pgscatalog/calc/lib/polygenicscore.py
pgscatalog/calc/lib/principalcomponents.py
pgscatalog/calc/lib/_ancestry/__init__.py
pgscatalog/calc/lib/_ancestry/read.py
pgscatalog/calc/lib/_ancestry/tools.py
pgscatalog_calc-0.3.1.dist-info/licenses/LICENSE
pgscatalog_calc-0.3.1.dist-info/METADATA
pgscatalog_calc-0.3.1.dist-info/WHEEL
pgscatalog_calc-0.3.1.dist-info/entry_points.txt
pgscatalog_calc-0.3.1.dist-info/top_level.txt
pgscatalog_calc-0.3.1.dist-info/RECORD
