Metadata-Version: 2.4
Name: pgscatalog.calc
Version: 0.3.1
Summary: Libraries and applications for working with calculated polygenic scores
Author-email: Benjamin Wingfield <bwingfield@ebi.ac.uk>, Samuel Lambert <sl925@medschl.cam.ac.uk>, Laurent Gil <lg10@sanger.ac.uk>, Florent Yvon <fy279@cam.ac.uk>
License-Expression: Apache-2.0
Classifier: Development Status :: 5 - Production/Stable
Classifier: Environment :: Console
Classifier: Intended Audience :: Science/Research
Classifier: Programming Language :: Python
Classifier: Programming Language :: Python :: 3
Classifier: Programming Language :: Python :: 3.10
Classifier: Programming Language :: Python :: 3.11
Classifier: Programming Language :: Python :: 3.12
Requires-Python: >=3.10
License-File: LICENSE
Requires-Dist: numpy~=1.26
Requires-Dist: pandas~=2.2.0
Requires-Dist: pyarrow~=15.0.0
Requires-Dist: scikit-learn~=1.4
Requires-Dist: scipy~=1.12
Requires-Dist: pgscatalog-core
Dynamic: license-file
